Workbook

Sheet ORDINI EVASI (3)
A1: ORDINI ELTHUB - EVASI
E2: =SUM(E6:E1318) -> 4366334.2 | F2: =SUM(F6:F1318) -> -0.0097 | G2: =SUM(G6:G1318) -> 4366334.2 | N2: VALUTA CAMBIO USD AL 31/03/2025: | O2: 0.93
N3: VALUTA CAMBIO GBP AL 31/08/2025: | O3: 1.15 | Q3: =SUM(Q6:Q1347) -> 130967.16 | R3: =SUM(R6:R1347) -> 131366.78 | S3: =SUM(S6:S1347) -> 159104.8 | T3: =SUM(T6:T1347) -> 368481.16 | U3: =SUM(U6:U1347) -> 195029.63 | V3: =SUM(V6:V1347) -> 434341.94 | W3: =SUM(W6:W1347) -> 181121.12 | X3: =SUM(X6:X1347) -> 260363.98 | ... AE3: =SUM(AE6:AE1347) -> 0
A5: OPERATORE | B5: NUMERO | C5: DATA | D5: FORNITORE | E5: IMPORTO TOTALE | F5: IMP. TOT. DA EVADERE | G5: IMP. TOT. EVASO | H5: DATA RICHIESTA | I5: DATA CONFERMAYA | J5: DATA EFFETTIVA | K5: JOB / CDC | L5: STATO | M5: CONFERMA | N5: NOTE | O5: VALUTA USD | P5: VALUTA GBP | Q5: MARZO | R5: APRILE | S5: MAGGIO | T5: GIUGNO | U5: LUGLIO | V5: AGOSTO | W5: SETTEMBRE | X5: OTTOBRE | Y5: NOVEMBRE | Z5: DICEMBRE | AA5: GENNAIO 2026 | AB5: FEBBRAIO 2026 | AC5: MARZO 2026 | AD5: APRILE 2026 | AE5: MAGGIO 2026
B6: 38 | C6: 45309 | D6: METATRON | E6: 165 | F6: =E6-G6 -> 0 | G6: 165 | K6: E-00071 (LCTE) | L6: EVASO
B7: 41 | C7: 45313 | D7: PONTECORVO | E7: 263.26 | F7: =E7-G7 -> 0 | G7: 263.26 | K7: E-00067 (EWE) | L7: EVASO
B8: 42 | C8: 45313 | D8: PONTECORVO | E8: 454.92 | F8: =E8-G8 -> 0 | G8: 454.92 | K8: E-00083 (PANALYTICAL) | L8: EVASO
B9: 44 | C9: 45313 | D9: PONTECORVO | E9: 89.32 | F9: =E9-G9 -> 0 | G9: 89.32 | K9: E-00091 (GOMA) | L9: EVASO
B10: 45 | C10: 45313 | D10: FARNELL | E10: 77.88 | F10: =E10-G10 -> 0 | G10: 77.88 | K10: E-00094 (PANALYTICAL) | L10: EVASO
B11: 414 | C11: 45278 | D11: AIR SERVICE | E11: 570 | F11: =E11-G11 -> 0 | G11: 570 | K11: CDC-07/40 (DIR STAB/MANUT IMPIANTI) | L11: EVASO
B12: 432 | C12: 45288 | D12: MOUSER | E12: 2420.86 | F12: =E12-G12 -> 0 | G12: 2420.86 | K12: E-00067 (EWE) | L12: EVASO
B13: 7 | C13: 45303 | D13: MONDOFFICE | E13: 1213.87 | F13: =E13-G13 -> 0 | G13: 1213.87 | K13: CDC-7/34 | L13: EVASO
B14: 11 | C14: 45300 | D14: DB ELECTRONIC | E14: 4543.01 | F14: =E14-G14 -> 0 | G14: 4543.01 | K14: E-00079 (QUIRIS) | L14: EVASO
B15: 419 | C15: 45279 | D15: LA NUOVA EUROGALV | E15: 445.4 | F15: =E15-G15 -> 0 | G15: 445.4 | K15: E-00083 (PANALYTICAL) | L15: EVASO
B16: 427 | C16: 45282 | D16: ELCO | E16: 5055 | F16: =E16-G16 -> 0 | G16: 5055 | H16: 45320 | K16: E-00067 (EWE) | L16: EVASO | M16: SCRITTA
B17: 36 | C17: 45309 | D17: LA NUOVA EUROGALV | E17: 115.5 | F17: =E17-G17 -> 0 | G17: 115.5 | H17: 45322 | K17: E-00091 (GOMA) | L17: EVASO
B18: 47 | C18: 45315 | D18: RS COMPONENTS | E18: 81.85 | F18: =E18-G18 -> 0 | G18: 81.85 | H18: 45321 | K18: I-P0001 (NUTRI 3D) | L18: EVASO | M18: SCRITTA
B19: 49 | C19: 45317 | D19: MOUSER | E19: 227.57 | F19: =E19-G19 -> 0 | G19: 227.57 | H19: 45322 | K19: E-00071 (LCTE) | L19: CONFERMATO | M19: SCRITTA
B20: 16 | C20: 45301 | D20: GLV TECHNOLOGY | E20: 1800 | F20: =E20-G20 -> 0 | G20: 1800 | H20: 45322 | K20: CDC-5/17 (PROD/CONSULENZE) | L20: CONFERMATO | M20: VERBALE
B21: 56 | C21: 45321 | D21: RS COMPONENTS | E21: 110.34 | F21: =E21-G21 -> 0 | G21: 110.34 | H21: 45323 | K21: AUDIO ASSY | L21: CONFERMATO | M21: SCRITTA
B22: 54 | C22: 45321 | D22: FARNELL | E22: 382.52 | F22: =E22-G22 -> 0 | G22: 382.52 | H22: 45323 | K22: AUDIO ASSY | L22: CONFERMATO | M22: SCRITTA
B23: 415 | C23: 45279 | D23: SOLYNX | E23: =O23*O2 -> 1186.5312 | F23: =E23-G23 -> 0.0012 | G23: 1186.53 | H23: 45310 | K23: ELT 4500062051 | L23: INVIATO | M23: SCRITTA | N23: ORDINE EMESSO IN VALUTA USD | O23: 1275.84
B24: 23 | C24: 45303 | D24: QUASER | E24: 1321 | F24: =E24-G24 -> 0 | G24: 1321 | H24: 44966 | K24: INVESTIMENTO | L24: CONS. PARZ. | M24: SCRITTA
B25: 60 | C25: 45322 | D25: RS COMPONENTS | E25: 48.36 | F25: =E25-G25 -> 0 | G25: 48.36 | H25: 45324 | K25: E-00083 (PANALYTICAL) | L25: INVIATO | M25: SCRITTA
B26: 3 | C26: 45299 | D26: ELCO | E26: 1311 | F26: =E26-G26 -> 0 | G26: 1311 | H26: 45306 | K26: E-00079 (QUIRIS) | L26: CONFERMATO | M26: SCRITTA
B27: 59 | C27: 45322 | D27: PROVAL SERVICE | E27: 90.86 | F27: =E27-G27 -> 0 | G27: 90.86 | H27: 45324 | K27: E-00079 (QUIRIS) | L27: CONFERMATO | M27: SCRITTA
B28: 65 | C28: 45324 | D28: CECASA | E28: 3120 | F28: =E28-G28 -> 0 | G28: 3120 | H28: 45324 | K28: E-00071 (LCTE) | L28: CONFERMATO | M28: VERBALE
B29: 50 | C29: 45317 | D29: LA NUOVA EUROGALV | E29: 145 | F29: =E29-G29 -> 0 | G29: 145 | H29: 45327 | K29: E-00091 (GOMA) | L29: CONFERMATO | M29: SCRITTA
B30: 343 | C30: 45251 | D30: AVIATRONIK | E30: 3450 | F30: =E30-G30 -> 0 | G30: 3450 | H30: 45336 | K30: CDC 5/21 (PROD/MANUT. STRUMENTI) | L30: INVIATO
B31: 2 | C31: 45320 | D31: PF ELETTRONICA | E31: 2080 | F31: =E31-G31 -> 0 | G31: 2080 | H31: 45327 | K31: E-00067 (EWE) | L31: INVIATO
B32: 73 | C32: 45328 | D32: STAMPA E TAGLIO | E32: 45 | F32: =E32-G32 -> 0 | G32: 45 | H32: 45328 | K32: E-00083 (PANALYTICAL) | L32: INVIATO
B33: 69 | C33: 45327 | D33: GCI | E33: 84 | F33: =E33-G33 -> 0 | G33: 84 | H33: 45334 | K33: CDC-11/54 (INF. TECH/SPESE HARDWARE) | L33: CONFERMATO | M33: SCRITTA
B34: 230 | C34: 45204 | D34: OFFICINE LAMERA | E34: 62000 | F34: =E34-G34 -> 0 | G34: 62000 | H34: 45260 | K34: I-P0001 (INIZIALE QUIRIS) | L34: CONS. PARZ.
B35: 68 | C35: 45327 | D35: MONDOFFICE | E35: 239 | F35: =E35-G35 -> 0 | G35: 239 | H35: 45334 | K35: CDC-11/54 (INF. TECH/SPESE HARDWARE) | L35: CONFERMATO | M35: SCRITTA
B36: 57 | C36: 45321 | D36: LA NUOVA EUROGALV | E36: 400 | F36: =E36-G36 -> 0 | G36: 400 | H36: 45329 | K36: E-00079 (QUIRIS) | L36: CONFERMATO | M36: VERBALE
B37: 10 | C37: 45300 | D37: GCI | E37: 1460 | F37: =E37-G37 -> 0 | G37: 1460 | H37: 45310 | K37: CDC-11/55 (INF. TECH/LIC. SOFTWARE) | L37: EVASO | M37: SCRITTA
B38: 37 | C38: 45308 | D38: LA NUOVA EUROGALV | E38: 833.4 | F38: =E38-G38 -> 0 | G38: 833.4 | H38: 45322 | K38: E-00067 (EWE) | L38: CONS. PARZ. | M38: SCRITTA
B39: 84 | C39: 45330 | D39: TECNOMILL | E39: 135 | F39: =E39-G39 -> 0 | G39: 135 | H39: 45334 | K39: CDC-5/18 (DIR PROD/MAT PROTITIPI) | L39: CONFERMATO | M39: SCRITTA
B40: 40 | C40: 45313 | D40: ASSELTECH | E40: 185 | F40: =E40-G40 -> 0 | G40: 185 | H40: 45324 | K40: E-00067 (EWE) | L40: CONFERMATO | M40: SCRITTA
B41: 58 | C41: 45321 | D41: ASSELTECH | E41: 185 | F41: =E41-G41 -> 0 | G41: 185 | H41: 45324 | K41: E-00091 (GOMA) | L41: INVIATO | M41: SCRITTA
B42: 81 | C42: 45330 | D42: F.LLI GUERRERO | E42: 170 | F42: =E42-G42 -> 0 | G42: 170 | H42: 45336 | K42: E-00083 (PANALYTICAL) | L42: INVIATO
B43: 88 | C43: 45331 | D43: PONTECORVO | E43: 204.12 | F43: =E43-G43 -> 0 | G43: 204.12 | H43: 45338 | K43: E-00067 (EWE) | L43: CONFERMATO | M43: TELEFONICA
B44: 89 | C44: 45331 | D44: PONTECORVO | E44: 36 | F44: =E44-G44 -> 0 | G44: 36 | H44: 45338 | K44: E-00068 (INFN) | L44: CONFERMATO | M44: TELEFONICA
B45: 74 | C45: 45328 | D45: LA NUOVA EUROGALV | E45: 233 | F45: =E45-G45 -> 0 | G45: 233 | H45: 45336 | K45: E-00067 (EWE) | L45: CONFERMATO | M45: SCRITTA
B46: 368 | C46: 45259 | D46: JAMPEL | E46: 2660 | F46: =E46-G46 -> 0 | G46: 2660 | H46: 45324 | K46: E-00067 (EWE) | L46: CONFERMATO | M46: SCRITTA
B47: 31 | C47: 45307 | D47: ALSCO | E47: 224 | F47: =E47-G47 -> 0 | G47: 224 | H47: 45310 | K47: CDC-5/19 (PROD/MAT CONSUMO) | L47: CONFERMATO | M47: SCRITTA
B48: 91 | C48: 45334 | D48: MOUSER | E48: 108.52 | F48: =E48-G48 -> 0 | G48: 108.52 | H48: 45337 | K48: E-00071 (LCTE) | L48: CONFERMATO | M48: SCRITTA
B49: 83 | C49: 45330 | D49: LA NUOVA EUROGALV | E49: 16.8 | F49: =E49-G49 -> 0 | G49: 16.8 | H49: 45337 | K49: E-00071 (LCTE) | L49: CONFERMATO | M49: SCRITTA
B50: 82 | C50: 45330 | D50: LA NUOVA EUROGALV | E50: 216.8 | F50: =E50-G50 -> 0 | G50: 216.8 | H50: 45337 | K50: E-00079 (QUIRIS) | L50: CONFERMATO | M50: SCRITTA
B51: 402 | C51: 45273 | D51: F.LLI GUERRERO | E51: 1139 | F51: =E51-G51 -> 0 | G51: 1139 | H51: 45306 | K51: E-00083 (PANALYTICAL) | L51: CONFERMATO | M51: SCRITTA
B52: 20 | C52: 45302 | D52: GALVANICA ITALIA | E52: 569.5 | F52: =E52-G52 -> 0 | G52: 569.5 | H52: 45322 | K52: E-00083 (PANALYTICAL) | L52: CONFERMATO | M52: VERBALE
B53: 77 | C53: 45329 | D53: METATRON | E53: 180.44 | F53: =E53-G53 -> 0 | G53: 180.44 | H53: 45342 | K53: E-00091 (GOMA) | L53: CONFERMATO | M53: SCRITTA
B54: 337 | C54: 45250 | D54: ELTREV | E54: 2851.5 | F54: =E54-G54 -> 0 | G54: 2851.5 | H54: 45306 | K54: E-00083 (PANALYTICAL) | L54: CONFERMATO | M54: SCRITTA
B55: 285 | C55: 45232 | D55: MOUSER | E55: 7634.1 | F55: =E55-G55 -> 0 | G55: 7634.1 | H55: 45237 | K55: I-P0001 (INIZIALE LCTE) | L55: CONS. PARZ. | M55: SCRITTA
B56: 93 | C56: 45336 | D56: FARNELL | E56: 24.36 | F56: =E56-G56 -> 0 | G56: 24.36 | H56: 45337 | K56: E-00083 (PANALYTICAL) | L56: INVIATO
B57: 90 | C57: 45334 | D57: METATRON | E57: 100 | F57: =E57-G57 -> 0 | G57: 100 | H57: 45343 | K57: E-00079 (QUIRIS) | L57: CONFERMATO | M57: SCRITTA
B58: 92 | C58: 45334 | D58: METATRON | E58: 160 | F58: =E58-G58 -> 0 | G58: 160 | H58: 45338 | K58: CDC-05/19 | L58: CONFERMATO | M58: SCRITTA
B59: 410 | C59: 45275 | D59: METATRON | E59: 1060.8 | F59: =E59-G59 -> 0 | G59: 1060.8 | H59: 45322 | K59: E-00083 (PANALYTICAL) | L59: CONS. PARZ. | M59: SCRITTA
B60: 93 | C60: 45336 | D60: FARNELL | E60: 24.36 | F60: =E60-G60 -> 0 | G60: 24.36 | H60: 45337 | K60: E-00083 (PANALYTICAL) | L60: CONFERMATO | M60: SCRITTA
B61: 81 | C61: 45330 | D61: F.LLI GUERRERO | E61: 170 | F61: =E61-G61 -> 0 | G61: 170 | H61: 45336 | K61: E-00083 (PANALYTICAL) | L61: CONFERMATO | M61: SCRITTA
B62: 94 | C62: 45336 | D62: UTOR | E62: 193 | F62: =E62-G62 -> 0 | G62: 193 | H62: 45342 | K62: CDC-5/20 | L62: CONFERMATO | M62: TELEFONICA
B63: 78 | C63: 45329 | D63: XOMETRY | E63: 106.52 | F63: =E63-G63 -> 0 | G63: 106.52 | H63: 45336 | K63: E-00079 (QUIRIS) | L63: CONFERMATO | M63: SCRITTA
B64: 394 | C64: 45272 | D64: ELETTRONICA SRLS | E64: 345 | F64: =E64-G64 -> 0 | G64: 345 | H64: 45275 | K64: E-00095 (LEONARDO) | L64: CONS. PARZ.
B65: 318 | C65: 45240 | D65: ELETTRONICA SRLS | E65: 4465 | F65: =E65-G65 -> 0 | G65: 4465 | H65: 45260 | K65: E-00088 (LEONARDO) | L65: CONS. PARZ.
B66: 102 | C66: 45342 | D66: MOUSER | E66: 201.69 | F66: =E66-G66 -> 0 | G66: 201.69 | H66: 45345 | K66: E-00103 (ELT 4500061938) | L66: INVIATO
B67: 104 | C67: 45342 | D67: RS COMPONENTS | E67: 63.77 | F67: =E67-G67 -> 0 | G67: 63.77 | H67: 45344 | K67: E-00083 (PANALYTICAL) | L67: INVIATO
B68: 95 | C68: 45341 | D68: PONTECORVO | E68: 1543.19 | F68: =E68-G68 -> 0 | G68: 1543.19 | H68: 45344 | K68: E-00103 (ELT 4500061938) | L68: CONFERMATO | M68: TELEFONICA
B69: 109 | C69: 45345 | D69: PROVAL SERVICE | E69: 90.86 | F69: =E69-G69 -> 0 | G69: 90.86 | H69: 45349 | K69: E-00072 (LEONARDO 8000253237) | L69: CONFERMATO | M69: SCRITTA
B70: 99 | C70: 45342 | D70: MONDO PLASTICA | E70: 133.9 | F70: =E70-G70 -> 0 | G70: 133.9 | H70: 45349 | K70: E-00103 (ELT 4500061938) | L70: INVIATO
B71: 112 | C71: 45345 | D71: RS COMPONENTS | E71: 17.94 | F71: =E71-G71 -> 0 | G71: 17.94 | H71: 45348 | K71: CDC-10/53 (GEST. MAG/MAT. A MAG.) | L71: INVIATO
B72: 106 | C72: 45344 | D72: GCI | E72: 145 | F72: =E72-G72 -> 0 | G72: 145 | H72: 45356 | K72: CDC-11/54 (INF. TECH./HARDWARE) | L72: INVIATO
B73: 103 | C73: 45342 | D73: BOSSARD | E73: 57.2 | F73: =E73-G73 -> 0 | G73: 57.2 | H73: 45351 | K73: E-00083 (PANALYTICAL) | L73: INVIATO
B74: 107 | C74: 45344 | D74: HOFFMANN | E74: 596.67 | F74: =E74-G74 -> 0 | G74: 596.67 | H74: 45348 | K74: CDC-05/19 (PROD/MAT CONSUMO) | L74: INVIATO
B75: 101 | C75: 45342 | D75: LA NUOVA EUROGALV | E75: 40 | F75: =E75-G75 -> 0 | G75: 40 | H75: 45349 | K75: E-00068 (INFN) | L75: CONFERMATO | M75: SCRITTA
B76: 75 | C76: 45328 | D76: LA NUOVA EUROGALV | E76: 164 | F76: =E76-G76 -> 0 | G76: 164 | H76: 45338 | K76: E-00079 (QUIRIS) | L76: CONS. PARZ.
B77: 80 | C77: 45329 | D77: XOMETRY | E77: 155.56 | F77: =E77-G77 -> 0 | G77: 155.56 | H77: 45336 | K77: CDC-5/18 (DIR PROD/MAT PROTITIPI) | L77: CONFERMATO | M77: SCRITTA
B78: 86 | C78: 45331 | D78: XOMETRY | E78: 178.9 | F78: =E78-G78 -> 0 | G78: 178.9 | H78: 45341 | K78: CDC-5/18 (DIR PROD/MAT PROTITIPI) | L78: CONFERMATO | M78: SCRITTA
B79: 63 | C79: 45323 | D79: GLV TECHNOLOGY | E79: 2400 | F79: =E79-G79 -> 0 | G79: 2400 | H79: 45351 | K79: CDC-5/17 (PRODUZ/CONSULENZA) | L79: CONFERMATO | M79: VERBALE
B80: 113 | C80: 45348 | D80: ASSELTECH | E80: 60 | F80: =E80-G80 -> 0 | G80: 60 | H80: 45349 | K80: E-00091 (GOMA) | L80: INVIATO
B81: 72 | C81: 45328 | D81: PIERGIACOMI FORNITURE | E81: 768 | F81: =E81-G81 -> 0 | G81: 768 | H81: 45338 | K81: CDC-5/19 (PROD/MAT CONSUMO) | L81: CONFERMATO | M81: SCRITTA
B82: 116 | C82: 45349 | D82: GCI | E82: 140 | F82: =E82-G82 -> 0 | G82: 140 | H82: 45351 | K82: CDC-11/54 (INF. TECH./HARDWARE) | L82: INVIATO
B83: 118 | C83: 45349 | D83: LA NUOVA EUROGALV | E83: 50 | F83: =E83-G83 -> 0 | G83: 50 | H83: 45356 | K83: E-00079 (QUIRIS) | L83: CONFERMATO
B84: 33 | C84: 45308 | D84: CECASA | E84: 2500 | F84: =E84-G84 -> 0 | G84: 2500 | H84: 45336 | K84: E-00102 (ELT 4500062051) | L84: CONFERMATO | M84: SCRITTA
B85: 66 | C85: 45327 | D85: CECASA | E85: 3100 | F85: =E85-G85 -> 0 | G85: 3100 | H85: 45338 | K85: E-00104 (ELT 4500062233) | L85: CONFERMATO | M85: SCRITTA
B86: 122 | C86: 45351 | D86: LA NUOVA EUROGALV | E86: 51 | F86: =E86-G86 -> 0 | G86: 51 | H86: 45358 | K86: (ELT 4500062572) | L86: CONFERMATO
B87: 105 | C87: 45344 | D87: GCI | E87: 450 | F87: =E87-G87 -> 0 | G87: 450 | H87: 45345 | K87: CDC-11/55 (INF.TECH/LICENZE) | L87: INVIATO
B88: 138 | C88: 45355 | D88: TECNOMILL | E88: 831 | F88: =E88-G88 -> 0 | G88: 831 | H88: 45356 | K88: E-00079 (QUIRIS) | L88: INVIATO
B89: 13 | C89: 45301 | D89: MITOR SYSTEM | E89: 400 | F89: =E89-G89 -> 0 | G89: 400 | H89: 45342 | K89: E-00079 (QUIRIS) | L89: CONFERMATO | M89: SCRITTA
B90: 61 | C90: 45322 | D90: MITOR SYSTEM | E90: 312 | F90: =E90-G90 -> 0 | G90: 312 | H90: 45351 | K90: E-00091 (GOMA) | L90: CONFERMATO | M90: SCRITTA
B91: 62 | C91: 45322 | D91: MITOR SYSTEM | E91: 513 | F91: =E91-G91 -> 0 | G91: 513 | H91: 45351 | K91: E-00067 (EWE) | L91: CONFERMATO | M91: SCRITTA
B92: 79 | C92: 45329 | D92: PARIANI | E92: 165.5 | F92: =E92-G92 -> 0 | G92: 165.5 | H92: 45337 | K92: E-00067 (EWE) | L92: INVIATO
B93: 55 | C93: 45321 | D93: MOUSER | E93: 1266.43 | F93: =E93-G93 -> 0 | G93: 1266.43 | H93: 45323 | K93: E-00105 (AUDIO ASSY) | L93: CONS. PARZ. | M93: SCRITTA
B94: 136 | C94: 45355 | D94: DISTRELEC | E94: 185.22 | F94: =E94-G94 -> 0 | G94: 185.22 | H94: 45357 | K94: E-00110 (LEONARDO 1400099687) | L94: CONFERMATO | M94: SCRITTA
B95: 133 | C95: 45355 | D95: RS COMPONENTS | E95: 172.27 | F95: =E95-G95 -> 0 | G95: 172.27 | H95: 45357 | K95: E-00110 (LEONARDO 1400099687) | L95: CONFERMATO | M95: SCRITTA
B96: 121 | C96: 45351 | D96: LA NUOVA EUROGALV | E96: 424 | F96: =E96-G96 -> 0 | G96: 424 | H96: 45358 | K96: E-00079 (QUIRIS) | L96: CONFERMATO | M96: SCRITTA
B97: 117 | C97: 45349 | D97: LA NUOVA EUROGALV | E97: 136 | F97: =E97-G97 -> 0 | G97: 136 | H97: 45356 | K97: E-00067 (EWE) | L97: CONFERMATO | M97: SCRITTA
B98: 98 | C98: 45342 | D98: LA NUOVA EUROGALV | E98: 148 | F98: =E98-G98 -> 0 | G98: 148 | H98: 45349 | K98: E-00067 (EWE) | L98: CONFERMATO
B99: 128 | C99: 45352 | D99: LA NUOVA EUROGALV | E99: 38 | F99: =E99-G99 -> 0 | G99: 38 | H99: 45359 | K99: E-00079 (QUIRIS) | L99: CONFERMATO | M99: SCRITTA
B100: 129 | C100: 45352 | D100: LA NUOVA EUROGALV | E100: 30 | F100: =E100-G100 -> 0 | G100: 30 | H100: 45359 | K100: (ELT 4500062246) | L100: CONFERMATO | M100: SCRITTA
B101: 100 | C101: 45342 | D101: ELETTROLEGHE | E101: 2615 | F101: =E101-G101 -> 0 | G101: 2615 | H101: 45356 | K101: E-00103 (QUIRIS 5+2) | L101: CONFERMATO | M101: SCRITTA
...

Sheet CLASSE A (progettazione)
D1: REGISTRO FORNITORI QUALIFICATI TIPO A - ITEM E SERVIZI AL CLIENTE
L2: Certificato disponibile
L3: Certificazione verificata di web
L4: Certificazione verificata Accredia
L5: Certificazione scaduta - richiedere nuova
B7: POS. | C7: TIPO | D7: RAGIONE SOCIALE | E7: TIPO | F7: AMBITO DI FORNITURA | G7: CERTIFICAZIONE | H7: DISTRIBUTORE UFFICIALE O BROKER | I7: NOTE | J7: KPI QUALITA' | K7: KPI TEMPI | L7: CERTIFICAZIONI | M7: DATA SCADENZA CERTIFICAZIONE | N7: DATA INSERIMENTO | O7: INVIO CGA | P7: ACCETTAZIONE | Q7: NON ACCETTAZIONE
B8: 1 | C8: A | D8: D & P Electronic Systems Srl | E8: FORNITORE A SPECIFICA | F8: PROGETTAZIONE HW/SW, SVILUPPO DOCUMENTAZIONE E FORNITURA SCHEDE DIGITALI | L8: ISO 9001:2015 - certificato n. 12963
B9: 2 | C9: A | D9: PARIANI S.R.L. | E9: COSTRUTTORE | F9: SISTEMI DI ILLUMINAZIONE | L9: ISO 9001:2015 | M9: 45538 | O9: SI
B10: 3 | C10: A | D10: TECNOTTICA CONSONNI S.R.L. | E10: COSTRUTTORE | F10: COMPONENTI PER SISTEMI OTTICI | L10: ISO 9001:2015 | M10: 46221 | N10: 45404 | O10: SI | P10: SI
B11: 4 | C11: A | D11: ACX DESIGN S.R.L. | E11: COSTRUTTORE | F11: COSTRUTTORE CIRCUITI STAMPATI | L11: ISO 9001:2015 | M11: 46876 | N11: 45411
B12: 5 | C12: A | D12: ROTEM INDUSTRIES ISRAEL LTD | E12: COSTRUTTORE | F12: APPARATI TECNOLOGIE AVANZATE | L12: ISO 9001:2015 | N12: 45443
B13: 6 | C13: A | D13: DEEP LAB S.R.L. | E13: COSTRUTTORE | F13: PROGETTAZIONE E REALIZZAZIONE MACCHINARI, PARTICOLARI MECCANICI E IMPIANTI | L13: QUESTIONARIO PRE-QUALIFICA | N13: 45447
B14: 7 | C14: A | D14: C&C S.R.L. | E14: FORNITORE A SPECIFICA | L14: EN 9100:2018 | M14: 46184 | N14: 45469
B15: 8 | C15: A | D15: AVIATRONIK TRESCAL S.p.A. | E15: DISTRIBUTORE | F15: APPARECCHIATURE ELETTRONICHE | L15: ISO 9001:2015 | M15: 46960 | N15: 45583
B16: 9 | C16: A | D16: RACK PERUZZI | E16: COSTRUTTORE | F16: COSTRUZIONE RACK | L16: ISO 9001:2015 | M16: 46351 | N16: 45614
B17: 10 | C17: A | D17: GESTIONE SILO | E17: COSTRUTTORE | F17: DISPOSITIVI OTTICI | L17: ISO 9001:2015 | M17: 46374 | N17: 45938
B18: 11 | C18: A | D18: PECCHIOLI RESEARCH S.R.L. | E18: COSTRUTTORE | F18: COMPONENTI PER SISTEMI OTTICI | L18: ISO 9001:2015 | M18: 46532 | N18: 45404
B19: 12 | C19: A | D19: TESLAB S.R.L. | F19: LABORATORIO TEST | K19: ISO 9001:2015 | M19: 45580
B20: 13 | C20: A | D20: TS2 ENGINEERING | F20: PROGETTAZIONE | K20: ISO 9001:2015

Sheet CLASSE B (built to print)
D1: REGISTRO FORNITORI QUALIFICATI TIPO B - ITEM E SERVIZI AL CLIENTE
L2: Certificato disponibile
L3: Certificazione verificata di web
L4: Certificazione verificata Accredia
L5: Certificazione scaduta - richiedere nuova
B7: POS. | C7: TIPO | D7: RAGIONE SOCIALE | E7: TIPO | F7: AMBITO DI FORNITURA | G7: CERTIFICAZIONE | H7: DISTRIBUTORE UFFICIALE O BROKER | I7: NOTE | J7: KPI QUALITA' | K7: KPI TEMPI | L7: CERTIFICAZIONI | M7: DATA SCADENZA CERTIFICAZIONE | N7: DATA INSERIMENTO | O7: INVIO CGA | P7: ACCETTAZIONE | Q7: NON ACCETTAZIONE
B8: 1 | C8: B | D8: BRUNETTI & FIGLIO S.N.C. | E8: SUBFORNITORE | F8: PROCESSI DI VERNICIATURA TRATTAMENTI GALVANICI | L8: ISO 9001:2015 | M8: 46708 | O8: SI | P8: SI
B9: 2 | C9: B | D9: CIRCUITI STAMPATI S.R.L. | E9: SUBFORNITORE | F9: CIRCUITI STAMPATI MULTISTRATO RIGIDI E PER APPLICAZIONI MICROONDE | L9: ISO 9001:2015 | M9: 46563
B10: 3 | C10: B | D10: OFFICINE LAMERA S.R.L. | E10: COSTRUTTORE | F10: MATERIALI MECCANICI | L10: ISO 9001:2015 | M10: 46849 | O10: SI
B11: 4 | C11: B | D11: TECNOMILL S.R.L. | E11: COSTRUTTORE | F11: MATERIALI MECCANICI | L11: ISO 9001:2015 / EN 9100:2018 | M11: 46183 | O11: SI
B12: 5 | C12: B | D12: MITOR SYSTEM S.R.L. | E12: COSTRUTTORE | F12: MATERIALI MECCANICI | L12: ISO 9001:2015 | M12: 46399 | O12: SI | P12: SI
B13: 6 | C13: B | D13: METATRON S.R.L. | E13: COSTRUTTORE | F13: SERIGRAFIA | L13: ISO 9001:2015 | M13: 46430 | O13: SI | P13: SI
B14: 7 | C14: B | D14: ELETTRONICA SRLS | E14: COSTRUTTORE | F14: MONTAGGIO SCHEDE ELETTRONICHE | L14: ISO 9001:2015 | M14: 45720 | O14: SI
B15: 8 | C15: B | D15: F.LLI GUERRERO S.R.L. | E15: COSTRUTTORE | F15: VERNICIATURA | L15: ISO 9001:2015 | M15: 46720 | O15: SI
B16: 9 | C16: B | D16: SHENZEN JINSHENGDA ELECTRONIC & TECH CO. | E16: COSTRUTTORE | F16: COSTRUTTORE CIRCUITI STAMPATI | L16: ISO 9001:2015 | M16: 46493
B17: 10 | C17: B | D17: ELMACOM S.R.L. | E17: COSTRUTTORE | F17: CABLAGGI | L17: ISO 9001:2015 - n.CERT-08364-2001-AQ-ROM-SINCERT
B18: 11 | C18: B | D18: ASSELTECH S.R.L. | E18: COSTRUTTORE | F18: MONTAGGIO SCHEDE ELETTRONICHE | L18: ISO 9001:2015 | M18: 46794 | O18: SI | P18: SI
B19: 12 | C19: B | D19: CML F.LLI LIBERATI SRL | E19: COSTRUTTORE | F19: LAVORAZIONI MECCANICHE | L19: ISO 9001:2015 - certificato n. IT312812
B20: 13 | C20: B | D20: ELCO S.P.A. | E20: SUBFORNITORE | F20: CIRCUITI STAMPATI MULTISTRATO RIGIDI E PER APPLICAZIONI MICROONDE | L20: ISO 9001:2015 | M20: 45620
B21: 14 | C21: B | D21: CE.CA.SA. S.R.L. | E21: COSTRUTTORE | F21: LAVORAZIONI MECCANICHE | L21: ISO 9001:2015 | M21: 46222 | O21: SI | P21: SI
B22: 15 | C22: B | D22: LA NUOVA EUROGALV S.R.L. | E22: PRODUTTORE | F22: TRATTAMENTI GALVANICI | L22: ISO 9001:2015 | M22: 46753 | O22: SI | P22: SI
B23: 16 | C23: B | D23: GALVANICA ITALIA S.R.L. | E23: PRODUTTORE | F23: TRATTAMENTI GALVANICI | L23: ISO 9001:2015 | M23: 45682 | O23: SI
B24: 17 | C24: B | D24: MECCANICA INNOVATIVA S.R.L. | E24: COSTRUTTORE | F24: LAVORAZIONI MECCANICHE | L24: ISO 9001:2015 | M24: 46307 | O24: SI | P24: SI
B25: 18 | C25: B | D25: PROVAL SERVICE S.R.L. | E25: COSTRUTTORE | F25: LAMINE SERIGRAFICHE | L25: ISO 9001:2015 | M25: 46490 | O25: SI | P25: SI
B26: 19 | C26: B | D26: EL.TREV. S.R.L. | E26: COSTRUTTORE | F26: MONTAGGIO SCHEDE ELETTRONICHE | L26: ISO 9001:2015 / EN 9100:2018 | M26: 46193 | O26: SI
B27: 20 | C27: B | D27: PROTO LABS TOOLING GmbH | E27: COSTRUTTORE | F27: STAMPAGGIO, LAVORAZIONI CNC, STAMPA 3D | L27: ISO 9001:2015 | M27: 46521 | N27: 45355 | O27: SI
B28: 21 | C28: B | D28: GENEX RF srl | E28: PRODUTTORE | F28: COMPONENTI ELETTRONICI | L28: ISO 9001:2015 - certificato n. 9170.GEN2 | N28: 45363 | O28: SI | P28: SI
B29: 22 | C29: B | D29: TRATTAMENTI GALVANICI INDUSTRIALI S.R.L. | E29: PRODUTTORE | F29: TRATTAMENTI GALVANICI | L29: ISO 9001:2015 / EN 9100:2018 | M29: 45695 | N29: 45425 | O29: SI | P29: SI
B30: 23 | C30: B | D30: SUNKING CIRCUITS ELECTRONICS CO., LTD. | E30: COSTRUTTORE | F30: CIRCUITI STAMPATI | L30: ISO 9001:2015 | M30: 45515 | N30: 45495
B31: 24 | C31: B | D31: GOAN S.R.L. | E31: COSTRUTTORE | F31: LAVORAZIONI MECCANICHE | L31: ISO 9001:2015 | M31: 46315 | N31: 45552
B32: 25 | C32: B | D32: FG MECCANICA di FABRIZI GIORGIO | E32: COSTRUTTORE | F32: LAVORAZIONI MECCANICHE | L32: QUESTIONARIO PRE-QUALIFICA in attesa approvazione Spartaco | N32: 45558
B33: 26 | C33: B | D33: MATTIOCCO ELASTOMERI S.R.L. | E33: COSTRUTTORE | F33: MATERIALI PLASTICI | L33: ISO 9001:2015 | M33: 46595 | N33: 45562
B34: 27 | C34: B | D34: TECNOMEC S.R.L. | E34: COSTRUTTORE | F34: CIRCUITI STAMPATI | L34: ISO 9001:2015 | M34: 45439 | N34: 45572
B35: 28 | C35: B | D35: CISEL S.R.L. | E35: COSTRUTTORE | F35: CIRCUITI STAMPATI | L35: ISO 9001:2015 | M35: 46591 | N35: 45572
B36: 29 | C36: B | D36: MONDO PLASTICA S.R.L. | E36: DISTRIBUTORE | F36: MATERIE PLASTICHE | L36: QUESTIONARIO PRE-QUALIFICA in attesa approvazione Spartaco | N36: 45645
B37: 30 | C37: B | D37: CISTELAIER S.p.A. | E37: COSTRUTTORE | F37: CIRCUITI STAMPATI | L37: ISO 9001:2015 / EN 9100:2018 | M37: 22/02/2027 - 03/03/2026 | N37: 45671 | O37: SI
B38: 31 | C38: B | D38: LAMECO | E38: COSTRUTTORE | F38: LAVORAZIONI MECCANICHE | L38: ISO 9001:2015 / EN 9100:2018 | M38: 46472 | N38: 45671
B39: 32 | C39: B | D39: F.C.E. S.r.l. | E39: COSTRUTTORE | F39: LAVORAZIONI MECCANICHE | L39: ISO 9001:2015 | M39: 46173 | N39: 45790
B40: 33 | C40: B | D40: ALMET ITALIA S.r.l. | E40: DISTRIBUTORE | F40: MATERIE PRIME | L40: ISO 9001:2015 | M40: 45863 | N40: 45870 | O40: SI | P40: SI
B41: 34 | C41: B | D41: ALLUMINIO DI QUALITA' | E41: DISTRIBUTORE | F41: MATERIE PRIME | L41: ISO 9001:2015 | M41: 46568 | N41: 45908
B42: 35 | C42: B | D42: FRANCO CORRADI & C. S.A.S. | E42: DISTRIBUTORE | F42: COMPONENTI ELETTRONICI | L42: QUESTIONARIO PRE-QUALIFICA | N42: 45376

Sheet CLASSE C (coats)
D1: REGISTRO FORNITORI QUALIFICATI TIPO C- ITEM E SERVIZI AL CLIENTE
L2: Certificato disponibile
L3: Certificazione verificata di web
L4: Certificazione verificata Accredia
L5: Certificazione scaduta - richiedere nuova
B7: POS. | C7: TIPO | D7: RAGIONE SOCIALE | E7: TIPO | F7: AMBITO DI FORNITURA | G7: CERTIFICAZIONE | H7: DISTRIBUTORE UFFICIALE O BROKER | I7: NOTE | J7: KPI QUALITA' | K7: KPI TEMPI | L7: CERTIFICAZIONI | M7: DATA SCADENZA CERTIFICAZIONE | N7: DATA INSERIMENTO | O7: INVIO CGA | P7: ACCETTAZIONE | Q7: NON ACCETTAZIONE
B8: 1 | C8: C | D8: MILEXIA ITALIA S.P.A. | E8: DISTRIBUTORE | F8: COMPONENTI ELETTRONICI | L8: ISO 9001:2015 | M8: 46130
B9: 2 | C9: C | D9: SERVOTECNICA S.P.A. | E9: COSTRUTTORE | F9: COMPONENTI ELETTRONICI | L9: ISO 9001:2015 | M9: 46549 | O9: SI
B10: 3 | C10: C | D10: SOLYNX CORPORATION | E10: DISTRIBUTORE | F10: COMPONENTI ELETTRONICI | L10: ISO 9001:2015 | M10: 46132
B11: 4 | C11: C | D11: AVIATRONIK TRESCAL S.p.A. | E11: DISTRIBUTORE | F11: APPARECCHIATURE ELETTRONICHE | L11: ISO 9001:2015 | M11: 46960 | N11: 45583
B12: 5 | C12: C | D12: MAGI srl | E12: DISTRIBUTORE | F12: COMPONENTI MECCANICI DI PRECISIONE | L12: ISO 9001:2015 - certificato n. 1280
B13: 6 | C13: C | D13: BROWNELL LTD | E13: COSTRUTTORE | F13: PRODOTTI A CATALOGO | L13: ISO 9001:2015 | M13: 46488 | N13: 45385
B14: 7 | C14: C | D14: ACAL BFI ITALY srl | E14: DISTRIBUTORE | F14: COMPONENTI ELETTRONICI | L14: ISO 9001:2015 | M14: 46434 | N14: 45394

Sheet CLASSE D (distributori)
D1: REGISTRO FORNITORI QUALIFICATI TIPO D - ITEM E SERVIZI AL CLIENTE
L2: Certificato disponibile
L3: Certificazione verificata di web
L4: Certificazione verificata Accredia
L5: Certificazione scaduta - richiedere nuova
B7: POS. | C7: TIPO | D7: RAGIONE SOCIALE | E7: TIPO | F7: AMBITO DI FORNITURA | G7: CERTIFICAZIONE | H7: DISTRIBUTORE UFFICIALE O BROKER | I7: NOTE | J7: KPI QUALITA' | K7: KPI TEMPI | L7: CERTIFICAZIONI | M7: DATA SCADENZA CERTIFICAZIONE | N7: DATA INSERIMENTO | O7: INVIO CGA | P7: ACCETTAZIONE | Q7: NON ACCETTAZIONE
B8: 1 | C8: D | D8: MOUSER | E8: DISTRIBUTORE | F8: COMPONENTI ELETTRONICI | L8: ISO 9001-2015 / AS9100D | M8: 47004
B9: 2 | C9: D | D9: DIGI-KEY | E9: DISTRIBUTORE | F9: COMPONENTI ELETTRONICI | L9: ISO 9001:2015 | M9: 46118
B10: 3 | C10: D | D10: FARNELL ITALIA S.R.L. | E10: DISTRIBUTORE | F10: COMPONENTI ELETTRONICI | L10: ISO 9001:2015 | M10: 46682
B11: 4 | C11: D | D11: P.F. ELETTRONICA S.N.C. | E11: BROKER | F11: COMPONENTI ELETTRONICI | L11: ISO 9001:2015 | M11: 46735
B12: 5 | C12: D | D12: NICOMATIC SA | E12: COSTRUTTORE | F12: CONNETTORI | L12: ISO 9001:2015 | M12: 46181
B13: 6 | C13: D | D13: BOSSARD ITALIA S.R.L. | E13: DISTRIBUTORE | F13: DISTRIBUTORE VITERIA | L13: ISO 9001:2015 | M13: 46771
B14: 7 | C14: D | D14: AFAR S.R.L. | E14: BROKER | F14: COMPONENTI ELETTRONICI | L14: ISO 9001:2015 / EN 9120:2018 | M14: 46550
B15: 8 | C15: D | D15: LUMITRON | E15: COSTRUTTORE | F15: LED | L15: ISO 9001:2015 | M15: 46641
B16: 9 | C16: D | D16: MISUMI EUROPA GMBH | E16: DISTRIBUTORE | F16: MATERIALI MECCANICI | L16: ISO 9001:2015 | M16: 46741
B17: 10 | C17: D | D17: RS COMPONENTS S.R.L. | E17: DISTRIBUTORE | F17: COMPONENTI ELETTRONICI | L17: ISO 9001:2015 | M17: 46538
B18: 11 | C18: D | D18: ALHOF S.p.A. | E18: DISTRIBUTORE | F18: COMPONENTI ELETTROMECCANICI | L18: ISO 9001:2015 / EN 9120:2018 | M18: 46160 | N18: 45369 | O18: SI | P18: SI
B19: 12 | C19: D | D19: FUTURA S.R.L. | E19: COSTRUTTORE | F19: COMPONENTI ELETTRONICI | L19: ISO 9001:2015 | M19: 45683 | N19: 45399
B20: 13 | C20: D | D20: ELETTROLEGHE S.R.L. | E20: DISTRIBUTORE | F20: MATERIE PRIME | L20: QUESTIONARIO PRE-QUALIFICA | N20: 45421 | O20: SI | P20: SI
B21: 14 | C21: D | D21: NUOVA ITALACCIAI S.R.L. | E21: DISTRIBUTORE | F21: MATERIE PRIME | L21: QUESTIONARIO PRE-QUALIFICA | N21: 45433 | O21: SI | P21: SI
B22: 15 | C22: D | D22: J2 SOURCING AB | E22: DISTRIBUTORE | F22: COMPONENTI ELETTRONICI | L22: ISO 9001:2015 | M22: 46103 | N22: 45482
B23: 16 | C23: D | D23: DB ELECTRONIC INSTRUMENTS S.R.L. | E23: DISTRIBUTORE | F23: COMPONENTI ELETTRONICI | L23: QUESTIONARIO PRE-QUALIFICA in attesa approvazione Spartaco | N23: 45489
B24: 17 | C24: D | D24: SGA S.R.L. | E24: DISTRIBUTORE | F24: COMPONENTI ELETTRONICI | L24: ISO 9001:2015 | M24: 46809 | N24: 45489 | O24: SI | P24: SI
B25: 18 | C25: D | D25: A.B. ESSE S.P.A. | E25: COSTRUTTORE | F25: APPARECCHIATURE LASER | L25: QUESTIONARIO PRE-QUALIFICA in attesa approvazione Spartaco | N25: 45502
B26: 19 | C26: D | D26: NEXOS | E26: DISTRIBUTORE | F26: COMPONENTI ELETTRONICI | L26: QUESTIONARIO PRE-QUALIFICA in attesa approvazione Spartaco | N26: 45582
B27: 20 | C27: D | D27: PROMATEC S.p.A. | E27: DISTRIBUTORE | F27: COMPONENTI FLUIDODINAMICI | L27: ISO 9001:2015 | M27: 46702 | N27: 45607
B28: 21 | C28: D | D28: VIGO PHOTONICS S.A. | E28: COSTRUTTORE | F28: COMPONENTI ELETTRONICI | L28: ISO 9001:2015 | M28: 46921 | N28: 45644
B29: 22 | C29: D | D29: CELTE S.p.A. | E29: DISTRIBUTORE | F29: COMPONENTI ELETTRONICI | L29: ISO 9001:2015 | M29: 46802 | N29: 45673
B30: 23 | C30: D | D30: ADVAM S.R.L. | E30: DISTRIBUTORE | F30: COMPONENTI ELETTRONICI | L30: ISO 9001:2015 | M30: 45992 | N30: 45684 | O30: SI | P30: SI
B31: 24 | C31: D | D31: GLENAIR ITALIA S.p.A. | E31: PRODUTTORE | F31: COMPONENTI ELETTRONICI | L31: ISO 9001:2015 | M31: 46735 | N31: 45685
B32: 25 | C32: D | D32: SPECTROGON AB | E32: COSTRUTTORE | F32: COMPONENTI OTTICI | L32: ISO 9001:2015 | M32: 46917 | N32: 45687
B33: 26 | C33: D | D33: CONVERGE | E33: DISTRIBUTORE | F33: COMPONENTI ELETTRONICI | L33: ISO 9001:2015 | M33: 46758 | N33: 45721
B34: 27 | C34: D | D34: DIMAC RED S.p.A. | E34: DISTRIBUTORE | F34: COMPONENTI ELETTRONICI | L34: ISO 9001:2015 | M34: 46108 | N34: 45723
B35: 28 | C35: D | D35: TECHNOLOGY NUCLEAR ELECTRONICS SRL | E35: DISTRIBUTORE | F35: COMPONENTI ELETTRONICI | L35: ISO 9001:2015 - certificato n. 9115.TNE1 | N35: 45729
B36: 29 | C36: D | D36: PLABER | E36: COSTRUTTORE | N36: 45741
B37: 30 | C37: D | D37: ELESA S.p.A. | E37: PRODUTTORE | F37: COMPONENTI INDUSTRIALI | L37: ISO 9001:2015 | M37: 46846 | N37: 45761
B38: 31 | C38: D | D38: Microchip Technology Ireland Ltd. | E38: DISTRIBUTORI | F38: COMPONENTI ELETTRONICI | L38: ISO 9001:2015 | M38: 46536 | N38: 45802
B39: 32 | C39: D | D39: ARROW ELECTRONICS INC | E39: DISTRIBUTORE | F39: COMPONENTI ELETTRONICI | L39: ISO 9001:2015 | M39: 46068 | N39: 45812
B40: 33 | C40: D | D40: CONRAD ELECTRONIC ITALIA S.r.l. | E40: DISTRIBUTORE | F40: COMPONENTI ELETTRONICI | L40: ISO 9001:2015 | M40: 46773 | N40: 45859
B41: 34 | C41: D | D41: SAMTEC | E41: DISTRIBUTORE | F41: COMPONENTI ELETTRONICI | L41: ISO 9001:2015 | M41: 46371 | N41: 45925
B42: 35 | C42: D | D42: PACE UTENSILI | E42: DISTRIBUTORE | F42: UTENSILERIA E PRODOTTI PER OFFICINA
B43: 36 | C43: D | D43: AMADA | E43: COSTRUTTORE | F43: MACCHINARI PER PRODUZIONE
B44: 37 | C44: D | D44: RAVEDATI | E44: DISTRIBUTORE | F44: MACCHINARI PER PRODUZIONE
B45: 38 | C45: D | D45: TECNO GENERAL | E45: SERVIZI | F45: TELEFONIA, INTERNET
B46: 39 | C46: D | D46: PARTELLI | E46: DISTRIBUTORE | F46: ATTREZZATURE OTTICHE | M46: SI
B47: 40 | C47: D | D47: LASER OPTRONIC | E47: DISTRIBUTORE | F47: ATTREZZATURE OTTICHE
B48: 41 | C48: D | D48: COMELEC S.R.L. | E48: DISTRIBUTORE
B49: 42 | C49: D | D49: MITEC | E49: DISTRIBUTORE
B50: 43 | C50: D | D50: D.S.A | E50: DISTRIBUTORE
B51: 44 | C51: D | D51: CABIOTEC S.R.L. | E51: DISTRIBUTORE | F51: Materiali di consumo per il montaggio superficiale (SMT) e tradizionale di schede elettroniche. | K51: ISO 9001:2015 - certificato n. 60506 | N51: SI
B52: 45 | C52: D | D52: NOXANT | E52: DISTRIBUTORE | F52: TELECAMERE INFRAROSSI

Sheet CLASSE E (generali stabilimento
D1: REGISTRO FORNITORI QUALIFICATI TIPO E - ITEM E SERVIZI AL CLIENTE
L2: Certificato disponibile
L3: Certificazione verificata di web
L4: Certificazione verificata Accredia
L5: Certificazione scaduta - richiedere nuova
B7: POS. | C7: TIPO | D7: RAGIONE SOCIALE | E7: TIPO | F7: AMBITO DI FORNITURA | G7: CERTIFICAZIONE | H7: DISTRIBUTORE UFFICIALE O BROKER | I7: NOTE | J7: KPI QUALITA' | K7: KPI TEMPI | L7: CERTIFICAZIONI | M7: DATA SCADENZA CERTIFICAZIONE | N7: DATA INSERIMENTO | O7: INVIO CGA | P7: ACCETTAZIONE | Q7: NON ACCETTAZIONE
B9: 1 | C9: E | D9: MONDOFFICE | E9: DISTRIBUTORE | F9: CARTOLERIA, MATERIALI PER UFFICI
B10: 2 | C10: E | D10: LIBER S.R.L. | E10: PRODUTTORE | F10: PRODOTTI PER PULIZIA
B11: 3 | C11: E | D11: E.S.E. GEA S.R.L. | E11: SERVIZI | F11: MANUTENZIONE FABBRICATI
B12: 4 | C12: E | D12: FENICE MULTISERVIZI S.R.L. | E12: SERVIZI | F12: PULIZIA, SFALCIO ERBA, FACCHINAGGIO
B13: 5 | C13: E | D13: AIRSERVICE S.R.L. | E13: ASSISTENZA TECNICA | F13: INSTALLAZIONE E ASSISTENZA IMPIANTI TECNOLOGICI
B14: 6 | C14: E | D14: CATAPANO MAURO | E14: LIBERO PROFESSIONISTA | F14: ASSISTENZA IMPIANTI IDRAULICI
B15: 7 | C15: E | D15: TECNOCLIMA S.R.L. | E15: ASSISTENZA TECNICA | F15: MANUTENZIONE IMPIANTI
B16: 8 | C16: E | D16: HSC | E16: DISTRIBUTORE | F16: PRODOTTI VARI PER AZIENDE (PULIZIA / IMBALLAGGIO / ANTINFORTUNISTICA)
B17: 9 | C17: E | D17: ANTINCENDIO 2005 | E17: SERVIZI | F17: ANTINCENDIO, MANUTENZIONE ESTINTORI
B18: 10 | C18: E | D18: PRAGMA | E18: SERVIZI | F18: SMALTIMENTO RIFIUTI
B19: 11 | C19: E | D19: PRAXIGROUP | E19: SERVIZI | F19: MEDICO COMPETENTE
B20: 12 | C20: E | D20: TECNO GENERAL | E20: SERVIZI | F20: TELEFONIA, INTERNET
... B33: 25 | C33: E | D33: AMINSTRUMENTS | E33: PRODUTTORE | F33: PRODOTTI E SERVIZI ESD / CLEAN ROOM
B34: 26 | C34: E | D34: CABIOTEC S.R.L. | E34: DISTRIBUTORE | F34: Materiali di consumo per il montaggio superficiale (SMT) e tradizionale di schede elettroniche. | K34: ISO 9001:2015 - certificato n. 60506 | N34: SI
B35: 27 | C35: E | D35: ANGELANTONI TEST TECHNOLOGIES S.R.L. | E35: PRODUTTORE | F35: SIMULAZIONI - CALIBRAZIONI | K35: ISO 9001:2015
B36: 28 | C36: E | D36: MARGARINI IMBALLI S.r.l. | E36: COSTRUTTORE | F36: IMBALLI A DISEGNO | L36: inviato QUESTIONARIO PREQUALIFICA | N36: 45806
B37: 29 | C37: E | D37: BERNER | F37: PRODOTTI VARI PER PRODUZIONE
B38: 30 | C38: E | D38: CDP | E38: SERVIZI | F38: TIPOGRAFIA
B39: 31 | C39: E | D39: HOFFMANN | E39: DISTRIBUTORE | F39: UTENSILERIA E PRODOTTI PER OFFICINA
B40: 32 | C40: E | D40: GENERAL COMPUTER | E40: DISTRIBUTORE | F40: PRODOTTI HARDWARE E LICENZE SOFTWARE
B41: 33 | C41: E | D41: DATAONE | E41: DISTRIBUTORE | F41: LICENZE SOFTWARE
B42: 34 | C42: E | D42: BELOTTI SISTEMI | E42: DISTRIBUTORE
B43: 35 | C43: E | D43: WETEC | E43: DISTRIBUTORE

Sheet NON UTILIZZATI (>2 ANNI)
D1: REGISTRO FORNITORI QUALIFICATI TIPO F - ITEM E SERVIZI AL CLIENTE
L2: Certificato disponibile
L3: Certificazione verificata di web
L4: Certificazione verificata Accredia
L5: Certificazione scaduta - richiedere nuova
B7: POS. | C7: TIPO | D7: RAGIONE SOCIALE | E7: TIPO | F7: AMBITO DI FORNITURA | G7: CERTIFICAZIONE | H7: DISTRIBUTORE UFFICIALE O BROKER | I7: NOTE | J7: KPI QUALITA' | K7: KPI TEMPI | L7: CERTIFICAZIONI | M7: DATA SCADENZA CERTIFICAZIONE | N7: DATA INSERIMENTO | O7: INVIO CGA | P7: ACCETTAZIONE | Q7: NON ACCETTAZIONE
B9: 24 | C9: B | D9: ELETTRONICA SRLS | E9: COSTRUTTORE | F9: MONTAGGIO SCHEDE ELETTRONICHE | L9: ISO 9001:2015 | M9: 45720 | O9: SI

Sheet SEPARAZIONE SHEET OLD

Sheet ITEM E SERVIZI AL CLIENTE
D1: REGISTRO FORNITORI QUALIFICATI - ITEM E SERVIZI AL CLIENTE
L2: Certificato disponibile
L3: Certificazione verificata di web
L4: Certificazione verificata Accredia
L5: Certificazione scaduta - richiedere nuova
B7: POS. | C7: TIPO | D7: RAGIONE SOCIALE | E7: TIPO | F7: AMBITO DI FORNITURA | G7: CERTIFICAZIONE | H7: DISTRIBUTORE UFFICIALE O BROKER | I7: NOTE | J7: KPI QUALITA' | K7: KPI TEMPI | L7: CERTIFICAZIONI | M7: DATA SCADENZA CERTIFICAZIONE | N7: DATA INSERIMENTO | O7: INVIO CGA | P7: ACCETTAZIONE | Q7: NON ACCETTAZIONE
B8: 1 | C8: B | D8: BRUNETTI & FIGLIO S.N.C. | E8: SUBFORNITORE | F8: PROCESSI DI VERNICIATURA TRATTAMENTI GALVANICI | L8: ISO 9001:2015 | M8: 46708 | O8: SI | P8: SI
B9: 2 | C9: B | D9: CIRCUITI STAMPATI S.R.L. | E9: SUBFORNITORE | F9: CIRCUITI STAMPATI MULTISTRATO RIGIDI E PER APPLICAZIONI MICROONDE | L9: ISO 9001:2015 | M9: 46563
B10: 3 | C10: A | D10: D & P Electronic Systems Srl | E10: FORNITORE A SPECIFICA | F10: PROGETTAZIONE HW/SW, SVILUPPO DOCUMENTAZIONE E FORNITURA SCHEDE DIGITALI | L10: ISO 9001:2015 - certificato n. 12963
B11: 7 | C11: D | D11: MOUSER | E11: DISTRIBUTORE | F11: COMPONENTI ELETTRONICI | L11: ISO 9001-2015 / AS9100D | M11: 47004
B12: 8 | C12: D | D12: DIGI-KEY | E12: DISTRIBUTORE | F12: COMPONENTI ELETTRONICI | L12: ISO 9001:2015 | M12: 46118
B13: 9 | C13: D | D13: FARNELL ITALIA S.R.L. | E13: DISTRIBUTORE | F13: COMPONENTI ELETTRONICI | L13: ISO 9001:2015 | M13: 46682
B14: 10 | C14: D | D14: P.F. ELETTRONICA S.N.C. | E14: BROKER | F14: COMPONENTI ELETTRONICI | L14: ISO 9001:2015 | M14: 46735
B15: 11 | C15: D | D15: NICOMATIC SA | E15: COSTRUTTORE | F15: CONNETTORI | L15: ISO 9001:2015 | M15: 46181
B16: 12 | C16: C | D16: MILEXIA ITALIA S.P.A. | E16: DISTRIBUTORE | F16: COMPONENTI ELETTRONICI | L16: ISO 9001:2015 | M16: 46130
B17: 13 | C17: C | D17: SERVOTECNICA S.P.A. | E17: COSTRUTTORE | F17: COMPONENTI ELETTRONICI | L17: ISO 9001:2015 | M17: 46549 | O17: SI
B18: 14 | C18: D | D18: BOSSARD ITALIA S.R.L. | E18: DISTRIBUTORE | F18: DISTRIBUTORE VITERIA | L18: ISO 9001:2015 | M18: 46771
B19: 15 | C19: D | D19: MAGI srl | E19: DISTRIBUTORE | F19: COMPONENTI MECCANICI DI PRECISIONE | L19: ISO 9001:2015 - certificato n. 1280
B20: 16 | C20: B | D20: OFFICINE LAMERA S.R.L. | E20: COSTRUTTORE | F20: MATERIALI MECCANICI | L20: ISO 9001:2015 | M20: 46849 | O20: SI
B21: 17 | C21: B | D21: TECNOMILL S.R.L. | E21: COSTRUTTORE | F21: MATERIALI MECCANICI | L21: ISO 9001:2015 / EN 9100:2018 | M21: 46183 | O21: SI
B22: 18 | C22: B | D22: MITOR SYSTEM S.R.L. | E22: COSTRUTTORE | F22: MATERIALI MECCANICI | L22: ISO 9001:2015 | M22: 46399 | O22: SI | P22: SI
B23: 19 | C23: D | D23: AFAR S.R.L. | E23: BROKER | F23: COMPONENTI ELETTRONICI | L23: ISO 9001:2015 / EN 9120:2018 | M23: 46550
B24: 23 | C24: B | D24: METATRON S.R.L. | E24: COSTRUTTORE | F24: SERIGRAFIA | L24: ISO 9001:2015 | M24: 46430 | O24: SI | P24: SI
B25: 24 | C25: B | D25: ELETTRONICA SRLS | E25: COSTRUTTORE | F25: MONTAGGIO SCHEDE ELETTRONICHE | L25: ISO 9001:2015 | M25: 45720 | O25: SI
B26: 25 | C26: B | D26: F.LLI GUERRERO S.R.L. | E26: COSTRUTTORE | F26: VERNICIATURA | L26: ISO 9001:2015 | M26: 46720 | O26: SI
B27: 26 | C27: B | D27: SHENZEN JINSHENGDA ELECTRONIC & TECH CO. | E27: COSTRUTTORE | F27: COSTRUTTORE CIRCUITI STAMPATI | L27: ISO 9001:2015 | M27: 46493
B28: 28 | C28: B | D28: ELMACOM S.R.L. | E28: COSTRUTTORE | F28: CABLAGGI | L28: ISO 9001:2015 - n.CERT-08364-2001-AQ-ROM-SINCERT
B29: 29 | C29: B | D29: ASSELTECH S.R.L. | E29: COSTRUTTORE | F29: MONTAGGIO SCHEDE ELETTRONICHE | L29: ISO 9001:2015 | M29: 46794 | O29: SI | P29: SI
B30: 30 | C30: D | D30: LUMITRON | E30: COSTRUTTORE | F30: LED | L30: ISO 9001:2015 | M30: 46641
B31: 34 | C31: B | D31: CML F.LLI LIBERATI SRL | E31: COSTRUTTORE | F31: LAVORAZIONI MECCANICHE | L31: ISO 9001:2015 - certificato n. IT312812
B32: 38 | C32: D | D32: MISUMI EUROPA GMBH | E32: DISTRIBUTORE | F32: MATERIALI MECCANICI | L32: ISO 9001:2015 | M32: 46741
B33: 39 | C33: B | D33: ELCO S.P.A. | E33: SUBFORNITORE | F33: CIRCUITI STAMPATI MULTISTRATO RIGIDI E PER APPLICAZIONI MICROONDE | L33: ISO 9001:2015 | M33: 45620
B34: 41 | C34: B | D34: CE.CA.SA. S.R.L. | E34: COSTRUTTORE | F34: LAVORAZIONI MECCANICHE | L34: ISO 9001:2015 | M34: 46222 | O34: SI | P34: SI
B35: 42 | C35: B | D35: LA NUOVA EUROGALV S.R.L. | E35: PRODUTTORE | F35: TRATTAMENTI GALVANICI | L35: ISO 9001:2015 | M35: 46753 | O35: SI | P35: SI
B36: 43 | C36: B | D36: GALVANICA ITALIA S.R.L. | E36: PRODUTTORE | F36: TRATTAMENTI GALVANICI | L36: ISO 9001:2015 | M36: 45682 | O36: SI
B37: 44 | C37: B | D37: MECCANICA INNOVATIVA S.R.L. | E37: COSTRUTTORE | F37: LAVORAZIONI MECCANICHE | L37: ISO 9001:2015 | M37: 46307 | O37: SI | P37: SI
B38: 45 | C38: B | D38: PROVAL SERVICE S.R.L. | E38: COSTRUTTORE | F38: LAMINE SERIGRAFICHE | L38: ISO 9001:2015 | M38: 46490 | O38: SI | P38: SI
B39: 46 | C39: D | D39: RS COMPONENTS S.R.L. | E39: DISTRIBUTORE | F39: COMPONENTI ELETTRONICI | L39: ISO 9001:2015 | M39: 46538
B40: 47 | C40: B | D40: EL.TREV. S.R.L. | E40: COSTRUTTORE | F40: MONTAGGIO SCHEDE ELETTRONICHE | L40: ISO 9001:2015 / EN 9100:2018 | M40: 46193 | O40: SI
B41: 48 | C41: A | D41: PARIANI S.R.L. | E41: COSTRUTTORE | F41: SISTEMI DI ILLUMINAZIONE | L41: ISO 9001:2015 | M41: 45538 | O41: SI
B42: 49 | C42: C | D42: SOLYNX CORPORATION | E42: DISTRIBUTORE | F42: COMPONENTI ELETTRONICI | L42: ISO 9001:2015 | M42: 46132
B43: 50 | C43: B | D43: PROTO LABS TOOLING GmbH | E43: COSTRUTTORE | F43: STAMPAGGIO, LAVORAZIONI CNC, STAMPA 3D | L43: ISO 9001:2015 | M43: 46521 | N43: 45355 | O43: SI
B44: 51 | C44: B | D44: GENEX RF srl | E44: PRODUTTORE | F44: COMPONENTI ELETTRONICI | L44: ISO 9001:2015 - certificato n. 9170.GEN2 | N44: 45363 | O44: SI | P44: SI
B45: 52 | C45: D | D45: ALHOF S.p.A. | E45: DISTRIBUTORE | F45: COMPONENTI ELETTROMECCANICI | L45: ISO 9001:2015 / EN 9120:2018 | M45: 46160 | N45: 45369 | O45: SI | P45: SI
B46: 53 | C46: D | D46: FRANCO CORRADI & C. S.A.S. | E46: DISTRIBUTORE | F46: COMPONENTI ELETTRONICI | L46: QUESTIONARIO PRE-QUALIFICA | N46: 45376
B47: 54 | C47: D | D47: BROWNELL LTD | E47: COSTRUTTORE | F47: PRODOTTI A CATALOGO | L47: ISO 9001:2015 | M47: 46488 | N47: 45385
B48: 55 | C48: D | D48: EDMUND OPTICS LTD | E48: COSTRUTTORE | F48: PRODOTTI A SPECIFICA | L48: ISO 9001:2015 | M48: 46597 | N48: 45392
B49: 56 | C49: D | D49: ACAL BFI ITALY srl | E49: DISTRIBUTORE | F49: COMPONENTI ELETTRONICI | L49: ISO 9001:2015 | M49: 46434 | N49: 45394
B50: 57 | C50: D | D50: FUTURA S.R.L. | E50: COSTRUTTORE | F50: COMPONENTI ELETTRONICI | L50: ISO 9001:2015 | M50: 45683 | N50: 45399
B51: 58 | C51: ? | D51: TECNOTTICA CONSONNI S.R.L. | E51: COSTRUTTORE | F51: COMPONENTI PER SISTEMI OTTICI | L51: ISO 9001:2015 | M51: 46221 | N51: 45404 | O51: SI | P51: SI
B52: 59 | C52: C | D52: PECCHIOLI RESEARCH S.R.L. | E52: COSTRUTTORE | F52: COMPONENTI PER SISTEMI OTTICI | L52: ISO 9001:2015 | M52: 46532 | N52: 45404
B53: 60 | C53: ? | D53: ACX DESIGN S.R.L. | E53: COSTRUTTORE | F53: COSTRUTTORE CIRCUITI STAMPATI | L53: ISO 9001:2015 | M53: 46876 | N53: 45411
B54: 61 | C54: D | D54: ELETTROLEGHE S.R.L. | E54: DISTRIBUTORE | F54: MATERIE PRIME | L54: QUESTIONARIO PRE-QUALIFICA | N54: 45421 | O54: SI | P54: SI
B55: 62 | C55: B | D55: TRATTAMENTI GALVANICI INDUSTRIALI S.R.L. | E55: PRODUTTORE | F55: TRATTAMENTI GALVANICI | L55: ISO 9001:2015 / EN 9100:2018 | M55: 45695 | N55: 45425 | O55: SI | P55: SI
B56: 63 | C56: D | D56: NUOVA ITALACCIAI S.R.L. | E56: DISTRIBUTORE | F56: MATERIE PRIME | L56: QUESTIONARIO PRE-QUALIFICA | N56: 45433 | O56: SI | P56: SI
B57: 65 | C57: A ? | D57: ROTEM INDUSTRIES ISRAEL LTD | E57: COSTRUTTORE | F57: APPARATI TECNOLOGIE AVANZATE | L57: ISO 9001:2015 | N57: 45443
B58: 66 | C58: A | D58: DEEP LAB S.R.L. | E58: COSTRUTTORE | F58: PROGETTAZIONE E REALIZZAZIONE MACCHINARI, PARTICOLARI MECCANICI E IMPIANTI | L58: QUESTIONARIO PRE-QUALIFICA | N58: 45447
B59: 67 | C59: A | D59: C&C S.R.L. | E59: FORNITORE A SPECIFICA | L59: EN 9100:2018 | M59: 46184 | N59: 45469
B60: 68 | C60: D | D60: J2 SOURCING AB | E60: DISTRIBUTORE | F60: COMPONENTI ELETTRONICI | L60: ISO 9001:2015 | M60: 46103 | N60: 45482
B61: 70 | C61: D | D61: DB ELECTRONIC INSTRUMENTS S.R.L. | E61: DISTRIBUTORE | F61: COMPONENTI ELETTRONICI | L61: QUESTIONARIO PRE-QUALIFICA in attesa approvazione Spartaco | N61: 45489
B62: 71 | C62: D | D62: SGA S.R.L. | E62: DISTRIBUTORE | F62: COMPONENTI ELETTRONICI | L62: ISO 9001:2015 | M62: 46809 | N62: 45489 | O62: SI | P62: SI
B63: 72 | C63: B | D63: SUNKING CIRCUITS ELECTRONICS CO., LTD. | E63: COSTRUTTORE | F63: CIRCUITI STAMPATI | L63: ISO 9001:2015 | M63: 45515 | N63: 45495
B64: 73 | C64: D | D64: A.B. ESSE S.P.A. | E64: COSTRUTTORE | F64: APPARECCHIATURE LASER | L64: QUESTIONARIO PRE-QUALIFICA in attesa approvazione Spartaco | N64: 45502
B65: 74 | C65: B | D65: GOAN S.R.L. | E65: COSTRUTTORE | F65: LAVORAZIONI MECCANICHE | L65: ISO 9001:2015 | M65: 46315 | N65: 45552
B66: 75 | C66: B | D66: FG MECCANICA di FABRIZI GIORGIO | E66: COSTRUTTORE | F66: LAVORAZIONI MECCANICHE | L66: QUESTIONARIO PRE-QUALIFICA in attesa approvazione Spartaco | N66: 45558
B67: 76 | C67: B | D67: MATTIOCCO ELASTOMERI S.R.L. | E67: COSTRUTTORE | F67: MATERIALI PLASTICI | L67: ISO 9001:2015 | M67: 46595 | N67: 45562
B68: 77 | C68: B | D68: TECNOMEC S.R.L. | E68: COSTRUTTORE | F68: CIRCUITI STAMPATI | L68: ISO 9001:2015 | M68: 45439 | N68: 45572
B69: 78 | C69: B | D69: CISEL S.R.L. | E69: COSTRUTTORE | F69: CIRCUITI STAMPATI | L69: ISO 9001:2015 | M69: 46591 | N69: 45572
B70: 79 | C70: D | D70: NEXOS | E70: DISTRIBUTORE | F70: COMPONENTI ELETTRONICI | L70: QUESTIONARIO PRE-QUALIFICA in attesa approvazione Spartaco | N70: 45582
B71: 81 | C71: C | D71: AVIATRONIK TRESCAL S.p.A. | E71: DISTRIBUTORE | F71: APPARECCHIATURE ELETTRONICHE | L71: ISO 9001:2015 | M71: 46960 | N71: 45583
B72: 82 | C72: D | D72: PROMATEC S.p.A. | E72: DISTRIBUTORE | F72: COMPONENTI FLUIDODINAMICI | L72: ISO 9001:2015 | M72: 46702 | N72: 45607
B73: 83 | C73: B ? | D73: RACK PERUZZI | E73: COSTRUTTORE | F73: COSTRUZIONE RACK | L73: ISO 9001:2015 | M73: 46351 | N73: 45614
B74: 84 | C74: D | D74: VIGO PHOTONICS S.A. | E74: COSTRUTTORE | F74: COMPONENTI ELETTRONICI | L74: ISO 9001:2015 | M74: 46921 | N74: 45644
B75: 85 | C75: B | D75: MONDO PLASTICA S.R.L. | E75: DISTRIBUTORE | F75: MATERIE PLASTICHE | L75: QUESTIONARIO PRE-QUALIFICA in attesa approvazione Spartaco | N75: 45645
B76: 86 | C76: B | D76: CISTELAIER S.p.A. | E76: COSTRUTTORE | F76: CIRCUITI STAMPATI | L76: ISO 9001:2015 / EN 9100:2018 | M76: 22/02/2027 - 03/03/2026 | N76: 45671 | O76: SI
B77: 87 | C77: B | D77: LAMECO | E77: COSTRUTTORE | F77: LAVORAZIONI MECCANICHE | L77: ISO 9001:2015 / EN 9100:2018 | M77: 46472 | N77: 45671
B78: 88 | C78: D | D78: CELTE S.p.A. | E78: DISTRIBUTORE | F78: COMPONENTI ELETTRONICI | L78: ISO 9001:2015 | M78: 46802 | N78: 45673
B79: 89 | C79: D | D79: ADVAM S.R.L. | E79: DISTRIBUTORE | F79: COMPONENTI ELETTRONICI | L79: ISO 9001:2015 | M79: 45992 | N79: 45684 | O79: SI | P79: SI
B80: 90 | C80: D | D80: GLENAIR ITALIA S.p.A. | E80: PRODUTTORE | F80: COMPONENTI ELETTRONICI | L80: ISO 9001:2015 | M80: 46735 | N80: 45685
B81: 91 | C81: D | D81: SPECTROGON AB | E81: COSTRUTTORE | F81: COMPONENTI OTTICI | L81: ISO 9001:2015 | M81: 46917 | N81: 45687
B82: 92 | C82: D | D82: CONVERGE | E82: DISTRIBUTORE | F82: COMPONENTI ELETTRONICI | L82: ISO 9001:2015 | M82: 46758 | N82: 45721
B83: 93 | C83: D | D83: DIMAC RED S.p.A. | E83: DISTRIBUTORE | F83: COMPONENTI ELETTRONICI | L83: ISO 9001:2015 | M83: 46108 | N83: 45723
B84: 94 | C84: D | D84: TECHNOLOGY NUCLEAR ELECTRONICS SRL | E84: DISTRIBUTORE | F84: COMPONENTI ELETTRONICI | L84: ISO 9001:2015 - certificato n. 9115.TNE1 | N84: 45729
B85: 95 | C85: D | D85: PLABER | E85: COSTRUTTORE | N85: 45741
B86: 96 | C86: D | D86: ELESA S.p.A. | E86: PRODUTTORE | F86: COMPONENTI INDUSTRIALI | L86: ISO 9001:2015 | M86: 46846 | N86: 45761
B87: 97 | C87: B | D87: F.C.E. S.r.l. | E87: COSTRUTTORE | F87: LAVORAZIONI MECCANICHE | L87: ISO 9001:2015 | M87: 46173 | N87: 45790
B88: 99 | C88: D | D88: Microchip Technology Ireland Ltd. | E88: DISTRIBUTORI | F88: COMPONENTI ELETTRONICI | L88: ISO 9001:2015 | M88: 46536 | N88: 45802
B89: 100 | C89: B | D89: MARGARINI IMBALLI S.r.l. | E89: COSTRUTTORE | F89: IMBALLI A DISEGNO | L89: inviato QUESTIONARIO PREQUALIFICA | N89: 45806
B90: 101 | C90: D | D90: ARROW ELECTRONICS INC | E90: DISTRIBUTORE | F90: COMPONENTI ELETTRONICI | L90: ISO 9001:2015 | M90: 46068 | N90: 45812
B91: 102 | C91: D | D91: CONRAD ELECTRONIC ITALIA S.r.l. | E91: DISTRIBUTORE | F91: COMPONENTI ELETTRONICI | L91: ISO 9001:2015 | M91: 46773 | N91: 45859
B92: 103 | C92: B | D92: ALMET ITALIA S.r.l. | E92: DISTRIBUTORE | F92: MATERIE PRIME | L92: ISO 9001:2015 | M92: 45863 | N92: 45870 | O92: SI | P92: SI
B93: 105 | C93: B | D93: ALLUMINIO DI QUALITA' | E93: DISTRIBUTORE | F93: MATERIE PRIME | L93: ISO 9001:2015 | M93: 46568 | N93: 45908
B94: 106 | C94: D | D94: SAMTEC | E94: DISTRIBUTORE | F94: COMPONENTI ELETTRONICI | L94: ISO 9001:2015 | M94: 46371 | N94: 45925
B95: 107 | C95: B | D95: GESTIONE SILO | E95: COSTRUTTORE | F95: DISPOSITIVI OTTICI | L95: ISO 9001:2015 | M95: 46374 | N95: 45938

Sheet ITEM E SERVIZI INTERNI
C1: REGISTRO FORNITORI QUALIFICATI - ITEM E SERVIZI INTERNI
K2: Certificato disponibile
K3: Certificazione verificata di web
K4: Certificazione verificata Accredia
C6: RAGIONE SOCIALE | D6: TIPO | E6: AMBITO DI FORNITURA | F6: CERTIFICAZIONE | G6: DISTRIBUTORE UFFICIALE O BROKER | H6: NOTE | I6: KPI QUALITA' | J6: KPI TEMPI | K6: CERTIFICAZIONI | L6: DATA INSERIMENTO | M6: INVIO CGA | N6: ACCETTAZIONE | O6: NON ACCETTAZIONE
B7: 1 | C7: E.S.E. GEA S.R.L. | D7: SERVIZI | E7: MANUTENZIONE FABBRICATI
B8: 2 | C8: FENICE MULTISERVIZI S.R.L. | D8: SERVIZI | E8: PULIZIA, SFALCIO ERBA, FACCHINAGGIO
B9: 3 | C9: AIRSERVICE S.R.L. | D9: ASSISTENZA TECNICA | E9: INSTALLAZIONE E ASSISTENZA IMPIANTI TECNOLOGICI
B10: 4 | C10: CATAPANO MAURO | D10: LIBERO PROFESSIONISTA | E10: ASSISTENZA IMPIANTI IDRAULICI
B11: 5 | C11: TECNOCLIMA S.R.L. | D11: ASSISTENZA TECNICA | E11: MANUTENZIONE IMPIANTI
B12: 6 | C12: LIBER S.R.L. | D12: PRODUTTORE | E12: PRODOTTI PER PULIZIA
B13: 7 | C13: HSC | D13: DISTRIBUTORE | E13: PRODOTTI VARI PER AZIENDE (PULIZIA / IMBALLAGGIO / ANTINFORTUNISTICA)
B14: 8 | C14: GENERAL COMPUTER | D14: DISTRIBUTORE | E14: PRODOTTI HARDWARE E LICENZE SOFTWARE
B15: 9 | C15: ANTINCENDIO 2005 | D15: SERVIZI | E15: ANTINCENDIO, MANUTENZIONE ESTINTORI
B16: 10 | C16: CSA TEAM S.R.L. | D16: CONSULENTE | E16: SICUREZZA NEI LUOGHI DI LAVORO
B17: 11 | C17: DATAONE | D17: DISTRIBUTORE | E17: LICENZE SOFTWARE
B18: 12 | C18: ETMAN | D18: CONSULENTE | E18: CERTIFICAZIONE 14001 E SA8000
... B27: 21 | C27: TECNO GENERAL | D27: SERVIZI | E27: TELEFONIA, INTERNET
B28: 22 | C28: 1855 | D28: DISTRIBUTORE | E28: FORNITURA CAFFE'
B29: 23 | C29: BERNER | E29: PRODOTTI VARI PER PRODUZIONE
B30: 24 | C30: CDP | D30: SERVIZI | E30: TIPOGRAFIA
B31: 25 | C31: HOFFMANN | D31: DISTRIBUTORE | E31: UTENSILERIA E PRODOTTI PER OFFICINA
B32: 26 | C32: MASSARO | D32: LIBERO PROFESSIONISTA | E32: ASSISTENZA CALDAIE
B33: 27 | C33: MITUTOYO | D33: COSTRUTTORE | E33: STRUMENTI DI MISURA
B34: 28 | C34: MAZAK | D34: ASSISTENZA TECNICA | E34: VENDITA E MANUTENZIONE MACCHINE UTENSILI
B35: 29 | C35: NEXT04 | D35: SERVIZI | E35: SERVIZI INFORMATICI
B36: 30 | C36: QUASER | D36: DISTRIBUTORE | E36: PRODOTTI ESD / CLEAN ROOM
B37: 31 | C37: COMELEC S.R.L. | D37: DISTRIBUTORE
B38: 32 | C38: D.P.I. | D38: DISTRIBUTORE | E38: PRODOTTI CHIMICI (VIGON)
B39: 33 | C39: BARBIERI S.R.L. | D39: DISTRIBUTORE | E39: PRODOTTI CHIMICI (ALPHA)
B40: 34 | C40: GENTILE MULTISERVIZI | D40: SERVIZI | E40: PULIZIA AREE VERDI
B41: 35 | C41: AMINSTRUMENTS | D41: PRODUTTORE | E41: PRODOTTI E SERVIZI ESD / CLEAN ROOM
B42: 37 | C42: PARTELLI | D42: DISTRIBUTORE | E42: ATTREZZATURE OTTICHE | M42: SI
B43: 38 | C43: LASER OPTRONIC | D43: DISTRIBUTORE | E43: ATTREZZATURE OTTICHE
B44: 39 | C44: MITEC | D44: DISTRIBUTORE
B45: 40 | C45: BELOTTI SISTEMI | D45: DISTRIBUTORE
B46: 41 | C46: D.S.A | D46: DISTRIBUTORE
B47: 42 | C47: WETEC | D47: DISTRIBUTORE
B48: 43 | C48: CABIOTEC S.R.L. | D48: DISTRIBUTORE | E48: Materiali di consumo per il montaggio superficiale (SMT) e tradizionale di schede elettroniche. | K48: ISO 9001:2015 - certificato n. 60506 | N48: SI
B49: 44 | C49: ANGELANTONI TEST TECHNOLOGIES S.R.L. | D49: PRODUTTORE | E49: SIMULAZIONI - CALIBRAZIONI | K49: ISO 9001:2015
B50: 45 | C50: TESLAB S.R.L. | E50: LABORATORIO TEST | K50: ISO 9001:2015 | M50: 45580
B51: 46 | C51: NOXANT | D51: DISTRIBUTORE | E51: TELECAMERE INFRAROSSI
B52: 47
B53: 48
B54: 49
B55: 50
B56: 51
B57: 52
B58: 53
B59: 54
B60: 55
B61: 56
B62: 57
B63: 58
... B94: 90

Sheet FORNITORI IN VALUTAZIONE
D1: REGISTRO FORNITORI QUALIFICATI - ITEM E SERVIZI AL CLIENTE
B7: POS. | C7: TIPO | D7: RAGIONE SOCIALE | E7: TIPO | F7: AMBITO DI FORNITURA | G7: CERTIFICAZIONE | H7: DISTRIBUTORE UFFICIALE O BROKER | I7: NOTE | J7: KPI QUALITA' | K7: KPI TEMPI | L7: CERTIFICAZIONI | M7: DATA SCADENZA CERTIFICAZIONE | N7: DATA INSERIMENTO | O7: INVIO CGA | P7: ACCETTAZIONE | Q7: NON ACCETTAZIONE
B8: 104 | C8: C | D8: SENRING ELECTRONICS Co. Limited | E8: COSTRUTTORE | F8: COMPONENTI ELETTRONICI | L8: ???

Sheet STORICO
D1: REGISTRO FORNITORI QUALIFICATI - ITEM E SERVIZI AL CLIENTE
L2: Certificato disponibile
L3: Certificazione verificata di web
L4: Certificazione verificata Accredia
B7: POS. | C7: TIPO | D7: RAGIONE SOCIALE | E7: TIPO | F7: AMBITO DI FORNITURA | G7: CERTIFICAZIONE | H7: DISTRIBUTORE UFFICIALE O BROKER | I7: NOTE | J7: KPI QUALITA' | K7: KPI TEMPI | L7: CERTIFICAZIONI | M7: DATA SCADENZA CERTIFICAZIONE | N7: DATA INSERIMENTO | O7: INVIO CGA | P7: ACCETTAZIONE | Q7: NON ACCETTAZIONE
B8: 1 | D8: W.L. GORE & ASSOCIATES (UK) LTD | E8: FORNITORE A CATALOGO | F8: PROGETTAZIONE, SVILUPPO E PRODUZIONE DI GUARNIZIONI E CAVI | L8: AS9100D / ISO 9001_2015
B9: 2 | D9: TTI ITALY Srl | E9: DISTRIBUTORE | F9: COMPONENTI ELETTRONICI | L9: ISO 9001:2015 / EN 9100:2018
B10: 3 | D10: TRANS-PART SRL | E10: BROKER | F10: COMPONENTI ELETTRONICI | L10: EN 9120-2018 / ISO 9001:2015
B11: 4 | C11: D | D11: A. PONTECORVO S.P.A. | E11: DISTRIBUTORE | F11: MATERIE PRIME | L11: ISO 9001:2015 | O11: SI
B12: 5 | D12: ALANTYS TECHNOLOGY | E12: BROKER | F12: COMPONENTI ELETTRONICI | L12: ISO 9001:2015
B13: 6 | D13: TECNO 77 | E13: COSTRUTTORE | F13: Master per circuiti stampati Assemblaggio schede | L13: ISO 9001:2015
B14: 7 | D14: ABIS CIRCUITS CO. LIMITED | E14: COSTRUTTORE | F14: COSTRUTTORE CIRCUITI STAMPATI | L14: ISO 9001:2015
B15: 8 | D15: CONTRADATA | E15: DISTRIBUTORE | F15: PC INDUSTRIALI | L15: ISO 9001:2015
B16: 9 | D16: GENERON SPA | E16: COSTRUTTORE | F16: STRUMENTAZIONI | L16: ISO 9001:2015 - n.CERT-17841-2006-AQ-BOL
B17: 10 | D17: TEKCELEO | E17: COSTRUTTORE | F17: STRUMENTAZIONI | L17: ISO 9001:2015
B18: 11 | D18: IPP | E18: DISTRIBUTORI | F18: Forniture Industriali per Elettronica | L18: ISO 9001:2015
B19: 10 | C19: D | D19: DISTRELEC ITALIA S.R.L. | E19: DISTRIBUTORE | F19: COMPONENTI ELETTRONICI | L19: ISO 9001:2015
